statv.py
statv-0.3.1.dist-info/WHEEL
statv-0.3.1.dist-info/METADATA
statv-0.3.1.dist-info/license_files/LICENSE
statv-0.3.1.dist-info/RECORD
