Metadata-Version: 2.1
Name: statv
Version: 0.3.1
Summary: a uniform status implementation for graia project
License: MIT
Author-email: GreyElaina <GreyElaina@outlook.com>
Requires-Python: >=3.8
